{
  "description": "Business intelligence report",
  "fields": [],
  "relationships": [],
  "properties": {
    "bi_server": {
      "type": "string",
      "description": "Name of the business intelligence tool server information",
      "readonly": true,
      "validated": false,
      "label": {
        "default": "Server information",
        "en": "Server information"
      }
    },
    "lineage_link": {
      "type": "string",
      "description": "Visually explore lineage information",
      "hidden": true,
      "readonly": true,
      "validated": false,
      "label": {
        "default": "Lineage link",
        "en": "Lineage link"
      }
    }
  },
  "localized_metadata_attributes": {
    "name": {
      "default": "Report",
      "en": "Report",
      "de": "Bericht",
      "es": "Informe",
      "fr": "Rapport",
      "it": "Report",
      "ja": "レポート",
      "ko": "보고서",
      "pt": "Relatório",
      "ru": "Отчет",
      "sv": "Rapport",
      "zh": "报告",
      "zh_TW": "報告"
    }
  },
  "global_search_searchable": [],
  "attribute_only": false,
  "is_column_custom_attribute": false,
  "version": 1,
  "name": "ibm_bi_report",
  "allow_decorators": true
}
